{
  "financial_metrics": [
    {
      "ticker": "301373",
      "report_period": "20250930",
      "period": "ttm",
      "currency": "CNY",
      "market_cap": 3420125029.0,
      "enterprise_value": null,
      "price_to_earnings_ratio": null,
      "price_to_book_ratio": null,
      "price_to_sales_ratio": null,
      "enterprise_value_to_ebitda_ratio": null,
      "enterprise_value_to_revenue_ratio": null,
      "free_cash_flow_yield": null,
      "peg_ratio": null,
      "gross_margin": 44.7386,
      "operating_margin": 33.9501,
      "net_margin": 28.061,
      "return_on_equity": 6.3528,
      "return_on_assets": 6.4038,
      "return_on_invested_capital": null,
      "asset_turnover": 0.2045,
      "inventory_turnover": null,
      "receivables_turnover": null,
      "days_sales_outstanding": null,
      "operating_cycle": null,
      "working_capital_turnover": null,
      "current_ratio": 6.4972,
      "quick_ratio": 6.2309,
      "cash_ratio": 3.5816,
      "operating_cash_flow_ratio": null,
      "debt_to_equity": 0.114,
      "debt_to_assets": 10.2366,
      "interest_coverage": null,
      "revenue_growth": 0.084872,
      "earnings_growth": 0.081485,
      "book_value_growth": null,
      "earnings_per_share_growth": 0.079545,
      "free_cash_flow_growth": null,
      "operating_income_growth": 0.091211,
      "ebitda_growth": null,
      "payout_ratio": null,
      "earnings_per_share": 0.95,
      "book_value_per_share": 15.2027,
      "free_cash_flow_per_share": null
    },
    {
      "ticker": "301373",
      "report_period": "20250630",
      "period": "ttm",
      "currency": "CNY",
      "market_cap": 3174978104.0,
      "enterprise_value": null,
      "price_to_earnings_ratio": null,
      "price_to_book_ratio": null,
      "price_to_sales_ratio": null,
      "enterprise_value_to_ebitda_ratio": null,
      "enterprise_value_to_revenue_ratio": null,
      "free_cash_flow_yield": null,
      "peg_ratio": null,
      "gross_margin": 43.7962,
      "operating_margin": 34.68,
      "net_margin": 28.4926,
      "return_on_equity": 4.0607,
      "return_on_assets": 4.1349,
      "return_on_invested_capital": null,
      "asset_turnover": 0.1294,
      "inventory_turnover": null,
      "receivables_turnover": null,
      "days_sales_outstanding": null,
      "operating_cycle": null,
      "working_capital_turnover": null,
      "current_ratio": 7.5683,
      "quick_ratio": 7.2279,
      "cash_ratio": 4.6336,
      "operating_cash_flow_ratio": null,
      "debt_to_equity": 0.1019,
      "debt_to_assets": 9.248,
      "interest_coverage": null,
      "revenue_growth": 0.032805,
      "earnings_growth": 0.065575,
      "book_value_growth": null,
      "earnings_per_share_growth": 0.071429,
      "free_cash_flow_growth": null,
      "operating_income_growth": 0.088675,
      "ebitda_growth": null,
      "payout_ratio": null,
      "earnings_per_share": 0.6,
      "book_value_per_share": 14.8523,
      "free_cash_flow_per_share": null
    },
    {
      "ticker": "301373",
      "report_period": "20250331",
      "period": "ttm",
      "currency": "CNY",
      "market_cap": 3185825312.9999995,
      "enterprise_value": null,
      "price_to_earnings_ratio": null,
      "price_to_book_ratio": null,
      "price_to_sales_ratio": null,
      "enterprise_value_to_ebitda_ratio": null,
      "enterprise_value_to_revenue_ratio": null,
      "free_cash_flow_yield": null,
      "peg_ratio": null,
      "gross_margin": 44.0172,
      "operating_margin": 35.0915,
      "net_margin": 28.7026,
      "return_on_equity": 1.9451,
      "return_on_assets": 1.9993,
      "return_on_invested_capital": null,
      "asset_turnover": 0.062,
      "inventory_turnover": null,
      "receivables_turnover": null,
      "days_sales_outstanding": null,
      "operating_cycle": null,
      "working_capital_turnover": null,
      "current_ratio": 9.6573,
      "quick_ratio": 9.271,
      "cash_ratio": 5.755,
      "operating_cash_flow_ratio": null,
      "debt_to_equity": 0.0848,
      "debt_to_assets": 7.8206,
      "interest_coverage": null,
      "revenue_growth": 0.08335200000000001,
      "earnings_growth": 0.064132,
      "book_value_growth": null,
      "earnings_per_share_growth": 0.074074,
      "free_cash_flow_growth": null,
      "operating_income_growth": 0.08436099999999999,
      "ebitda_growth": null,
      "payout_ratio": null,
      "earnings_per_share": 0.29,
      "book_value_per_share": 15.0409,
      "free_cash_flow_per_share": null
    },
    {
      "ticker": "301373",
      "report_period": "20250331",
      "period": "ttm",
      "currency": "CNY",
      "market_cap": 3185825312.9999995,
      "enterprise_value": null,
      "price_to_earnings_ratio": null,
      "price_to_book_ratio": null,
      "price_to_sales_ratio": null,
      "enterprise_value_to_ebitda_ratio": null,
      "enterprise_value_to_revenue_ratio": null,
      "free_cash_flow_yield": null,
      "peg_ratio": null,
      "gross_margin": 44.0172,
      "operating_margin": 35.0915,
      "net_margin": 28.7026,
      "return_on_equity": 1.9451,
      "return_on_assets": 1.9993,
      "return_on_invested_capital": null,
      "asset_turnover": 0.062,
      "inventory_turnover": null,
      "receivables_turnover": null,
      "days_sales_outstanding": null,
      "operating_cycle": null,
      "working_capital_turnover": null,
      "current_ratio": 9.6573,
      "quick_ratio": 9.271,
      "cash_ratio": 5.755,
      "operating_cash_flow_ratio": null,
      "debt_to_equity": 0.0848,
      "debt_to_assets": 7.8206,
      "interest_coverage": null,
      "revenue_growth": 0.08335200000000001,
      "earnings_growth": 0.064132,
      "book_value_growth": null,
      "earnings_per_share_growth": 0.074074,
      "free_cash_flow_growth": null,
      "operating_income_growth": 0.08436099999999999,
      "ebitda_growth": null,
      "payout_ratio": null,
      "earnings_per_share": 0.29,
      "book_value_per_share": 15.0409,
      "free_cash_flow_per_share": null
    },
    {
      "ticker": "301373",
      "report_period": "20241231",
      "period": "ttm",
      "currency": "CNY",
      "market_cap": 2753021670.0,
      "enterprise_value": null,
      "price_to_earnings_ratio": null,
      "price_to_book_ratio": null,
      "price_to_sales_ratio": null,
      "enterprise_value_to_ebitda_ratio": null,
      "enterprise_value_to_revenue_ratio": null,
      "free_cash_flow_yield": null,
      "peg_ratio": null,
      "gross_margin": 44.6917,
      "operating_margin": 34.4499,
      "net_margin": 28.1908,
      "return_on_equity": 8.7083,
      "return_on_assets": 8.812,
      "return_on_invested_capital": null,
      "asset_turnover": 0.2775,
      "inventory_turnover": null,
      "receivables_turnover": null,
      "days_sales_outstanding": null,
      "operating_cycle": null,
      "working_capital_turnover": null,
      "current_ratio": 8.1168,
      "quick_ratio": 7.8368,
      "cash_ratio": 5.1661,
      "operating_cash_flow_ratio": null,
      "debt_to_equity": 0.101,
      "debt_to_assets": 9.175,
      "interest_coverage": null,
      "revenue_growth": 0.16692,
      "earnings_growth": 0.080175,
      "book_value_growth": null,
      "earnings_per_share_growth": 0.050846999999999996,
      "free_cash_flow_growth": null,
      "operating_income_growth": 0.11575200000000001,
      "ebitda_growth": null,
      "payout_ratio": null,
      "earnings_per_share": 1.24,
      "book_value_per_share": 14.7512,
      "free_cash_flow_per_share": null
    },
    {
      "ticker": "301373",
      "report_period": "20241231",
      "period": "ttm",
      "currency": "CNY",
      "market_cap": 2753021670.0,
      "enterprise_value": null,
      "price_to_earnings_ratio": null,
      "price_to_book_ratio": null,
      "price_to_sales_ratio": null,
      "enterprise_value_to_ebitda_ratio": null,
      "enterprise_value_to_revenue_ratio": null,
      "free_cash_flow_yield": null,
      "peg_ratio": null,
      "gross_margin": 44.6917,
      "operating_margin": 34.4499,
      "net_margin": 28.1908,
      "return_on_equity": 8.7083,
      "return_on_assets": 8.812,
      "return_on_invested_capital": null,
      "asset_turnover": 0.2775,
      "inventory_turnover": null,
      "receivables_turnover": null,
      "days_sales_outstanding": null,
      "operating_cycle": null,
      "working_capital_turnover": null,
      "current_ratio": 8.1168,
      "quick_ratio": 7.8368,
      "cash_ratio": 5.1661,
      "operating_cash_flow_ratio": null,
      "debt_to_equity": 0.101,
      "debt_to_assets": 9.175,
      "interest_coverage": null,
      "revenue_growth": 0.16692,
      "earnings_growth": 0.080175,
      "book_value_growth": null,
      "earnings_per_share_growth": 0.050846999999999996,
      "free_cash_flow_growth": null,
      "operating_income_growth": 0.11575200000000001,
      "ebitda_growth": null,
      "payout_ratio": null,
      "earnings_per_share": 1.24,
      "book_value_per_share": 14.7512,
      "free_cash_flow_per_share": null
    },
    {
      "ticker": "301373",
      "report_period": "20240930",
      "period": "ttm",
      "currency": "CNY",
      "market_cap": 2749767506.9999995,
      "enterprise_value": null,
      "price_to_earnings_ratio": null,
      "price_to_book_ratio": null,
      "price_to_sales_ratio": null,
      "enterprise_value_to_ebitda_ratio": null,
      "enterprise_value_to_revenue_ratio": null,
      "free_cash_flow_yield": null,
      "peg_ratio": null,
      "gross_margin": 44.8007,
      "operating_margin": 33.196,
      "net_margin": 27.6893,
      "return_on_equity": 6.2406,
      "return_on_assets": 6.1604,
      "return_on_invested_capital": null,
      "asset_turnover": 0.2036,
      "inventory_turnover": null,
      "receivables_turnover": null,
      "days_sales_outstanding": null,
      "operating_cycle": null,
      "working_capital_turnover": null,
      "current_ratio": 9.6971,
      "quick_ratio": 9.4062,
      "cash_ratio": 6.3978,
      "operating_cash_flow_ratio": null,
      "debt_to_equity": 0.0886,
      "debt_to_assets": 8.1419,
      "interest_coverage": null,
      "revenue_growth": -0.058287000000000005,
      "earnings_growth": 0.064709,
      "book_value_growth": null,
      "earnings_per_share_growth": 0.011493999999999999,
      "free_cash_flow_growth": null,
      "operating_income_growth": 0.095998,
      "ebitda_growth": null,
      "payout_ratio": null,
      "earnings_per_share": 0.88,
      "book_value_per_share": 14.3875,
      "free_cash_flow_per_share": null
    },
    {
      "ticker": "301373",
      "report_period": "20240630",
      "period": "ttm",
      "currency": "CNY",
      "market_cap": null,
      "enterprise_value": null,
      "price_to_earnings_ratio": null,
      "price_to_book_ratio": null,
      "price_to_sales_ratio": null,
      "enterprise_value_to_ebitda_ratio": null,
      "enterprise_value_to_revenue_ratio": null,
      "free_cash_flow_yield": null,
      "peg_ratio": null,
      "gross_margin": 44.9477,
      "operating_margin": 33.6515,
      "net_margin": 28.2579,
      "return_on_equity": 4.0465,
      "return_on_assets": 3.9673,
      "return_on_invested_capital": null,
      "asset_turnover": 0.1303,
      "inventory_turnover": null,
      "receivables_turnover": null,
      "days_sales_outstanding": null,
      "operating_cycle": null,
      "working_capital_turnover": null,
      "current_ratio": 12.59,
      "quick_ratio": 12.1918,
      "cash_ratio": 8.1725,
      "operating_cash_flow_ratio": null,
      "debt_to_equity": 0.0725,
      "debt_to_assets": 6.7588,
      "interest_coverage": null,
      "revenue_growth": -0.002066,
      "earnings_growth": 0.121474,
      "book_value_growth": null,
      "earnings_per_share_growth": 0.018182,
      "free_cash_flow_growth": null,
      "operating_income_growth": 0.182534,
      "ebitda_growth": null,
      "payout_ratio": null,
      "earnings_per_share": 0.56,
      "book_value_per_share": 14.0718,
      "free_cash_flow_per_share": null
    },
    {
      "ticker": "301373",
      "report_period": "20240331",
      "period": "ttm",
      "currency": "CNY",
      "market_cap": null,
      "enterprise_value": null,
      "price_to_earnings_ratio": null,
      "price_to_book_ratio": null,
      "price_to_sales_ratio": null,
      "enterprise_value_to_ebitda_ratio": null,
      "enterprise_value_to_revenue_ratio": null,
      "free_cash_flow_yield": null,
      "peg_ratio": null,
      "gross_margin": 47.341,
      "operating_margin": 35.0589,
      "net_margin": 29.2477,
      "return_on_equity": 1.9527,
      "return_on_assets": 1.9306,
      "return_on_invested_capital": null,
      "asset_turnover": 0.0598,
      "inventory_turnover": null,
      "receivables_turnover": null,
      "days_sales_outstanding": null,
      "operating_cycle": null,
      "working_capital_turnover": null,
      "current_ratio": 8.0053,
      "quick_ratio": 7.7858,
      "cash_ratio": 6.0541,
      "operating_cash_flow_ratio": null,
      "debt_to_equity": 0.1078,
      "debt_to_assets": 9.7338,
      "interest_coverage": null,
      "revenue_growth": 0.020518,
      "earnings_growth": 0.180062,
      "book_value_growth": null,
      "earnings_per_share_growth": -0.035714,
      "free_cash_flow_growth": null,
      "operating_income_growth": 0.32037,
      "ebitda_growth": null,
      "payout_ratio": null,
      "earnings_per_share": 0.27,
      "book_value_per_share": 14.08,
      "free_cash_flow_per_share": null
    },
    {
      "ticker": "301373",
      "report_period": "20231231",
      "period": "ttm",
      "currency": "CNY",
      "market_cap": null,
      "enterprise_value": null,
      "price_to_earnings_ratio": null,
      "price_to_book_ratio": null,
      "price_to_sales_ratio": null,
      "enterprise_value_to_ebitda_ratio": null,
      "enterprise_value_to_revenue_ratio": null,
      "free_cash_flow_yield": null,
      "peg_ratio": null,
      "gross_margin": 41.1038,
      "operating_margin": 31.7378,
      "net_margin": 26.8292,
      "return_on_equity": 11.8085,
      "return_on_assets": 11.3591,
      "return_on_invested_capital": null,
      "asset_turnover": 0.3866,
      "inventory_turnover": null,
      "receivables_turnover": null,
      "days_sales_outstanding": null,
      "operating_cycle": null,
      "working_capital_turnover": null,
      "current_ratio": 6.9067,
      "quick_ratio": 6.7119,
      "cash_ratio": 4.9892,
      "operating_cash_flow_ratio": null,
      "debt_to_equity": 0.1271,
      "debt_to_assets": 11.2758,
      "interest_coverage": null,
      "revenue_growth": 0.08262,
      "earnings_growth": 0.372389,
      "book_value_growth": null,
      "earnings_per_share_growth": 0.053571,
      "free_cash_flow_growth": null,
      "operating_income_growth": 0.349371,
      "ebitda_growth": null,
      "payout_ratio": null,
      "earnings_per_share": 1.18,
      "book_value_per_share": 13.8077,
      "free_cash_flow_per_share": null
    }
  ],
  "line_items": [
    {
      "ticker": "301373",
      "report_period": "20250930",
      "period": "ttm",
      "currency": "CNY",
      "capital_expenditure": 54503717.55,
      "net_income": 103206452.88,
      "outstanding_shares": 108472091.0,
      "total_assets": 1838083135.61,
      "total_liabilities": 188156802.0,
      "shareholders_equity": 1649064656.62,
      "dividends_and_other_cash_distributions": 54236045.5,
      "gross_profit": 125005162.51,
      "revenue": 368149702.31,
      "free_cash_flow": -83638019.8322
    },
    {
      "ticker": "301373",
      "report_period": "20250630",
      "period": "ttm",
      "currency": "CNY",
      "capital_expenditure": 36379216.87,
      "depreciation_and_amortization": 13220963.04,
      "net_income": 65198143.23,
      "outstanding_shares": 108472091.0,
      "total_assets": 1776134723.53,
      "total_liabilities": 164256872.34,
      "shareholders_equity": 1611056346.97,
      "dividends_and_other_cash_distributions": 54236045.5,
      "gross_profit": 79447661.83,
      "revenue": 229035582.58,
      "free_cash_flow": -1949755.8194
    },
    {
      "ticker": "301373",
      "report_period": "20250331",
      "period": "ttm",
      "currency": "CNY",
      "capital_expenditure": 17398742.29,
      "net_income": 31428645.83,
      "outstanding_shares": 108472091.0,
      "total_assets": 1770795871.22,
      "total_liabilities": 138486870.62,
      "shareholders_equity": 1631522895.07,
      "gross_profit": 38453049.32,
      "revenue": 109583251.92,
      "free_cash_flow": -54791190.0705
    },
    {
      "ticker": "301373",
      "report_period": "20250331",
      "period": "ttm",
      "currency": "CNY",
      "capital_expenditure": 17398742.29,
      "net_income": 31428645.83,
      "outstanding_shares": 108472091.0,
      "total_assets": 1770795871.22,
      "total_liabilities": 138486870.62,
      "shareholders_equity": 1631522895.07,
      "gross_profit": 38453049.32,
      "revenue": 109583251.92,
      "free_cash_flow": -54791190.0705
    },
    {
      "ticker": "301373",
      "report_period": "20241231",
      "period": "ttm",
      "currency": "CNY",
      "capital_expenditure": 108611059.83,
      "depreciation_and_amortization": 18209316.69,
      "net_income": 134885495.7,
      "outstanding_shares": 108472091.0,
      "total_assets": 1762572068.68,
      "total_liabilities": 161716344.29,
      "shareholders_equity": 1600094249.24,
      "dividends_and_other_cash_distributions": 32541627.3,
      "gross_profit": 164807710.37,
      "revenue": 478902336.91,
      "free_cash_flow": -60802893.8059
    },
    {
      "ticker": "301373",
      "report_period": "20241231",
      "period": "ttm",
      "currency": "CNY",
      "capital_expenditure": 108611059.83,
      "depreciation_and_amortization": 18209316.69,
      "net_income": 134885495.7,
      "outstanding_shares": 108472091.0,
      "total_assets": 1762572068.68,
      "total_liabilities": 161716344.29,
      "shareholders_equity": 1600094249.24,
      "dividends_and_other_cash_distributions": 32541627.3,
      "gross_profit": 164807710.37,
      "revenue": 478902336.91,
      "free_cash_flow": -60802893.8059
    },
    {
      "ticker": "301373",
      "report_period": "20240930",
      "period": "ttm",
      "currency": "CNY",
      "capital_expenditure": 81818985.47,
      "net_income": 95430350.55,
      "outstanding_shares": 108472091.0,
      "total_assets": 1699782758.38,
      "total_liabilities": 138394148.61,
      "shareholders_equity": 1560639104.09,
      "dividends_and_other_cash_distributions": 32541627.3,
      "gross_profit": 114384040.46,
      "revenue": 345041116.79
    },
    {
      "ticker": "301373",
      "report_period": "20240630",
      "period": "ttm",
      "currency": "CNY",
      "capital_expenditure": 64734758.21,
      "depreciation_and_amortization": 8163464.78,
      "net_income": 61185900.84,
      "outstanding_shares": 108472091.0,
      "total_assets": 1637811654.69,
      "total_liabilities": 110696512.96,
      "shareholders_equity": 1526394654.38,
      "dividends_and_other_cash_distributions": 32541627.3,
      "gross_profit": 72823755.61,
      "revenue": 216810191.17,
      "free_cash_flow": -81299376.5225
    },
    {
      "ticker": "301373",
      "report_period": "20240331",
      "period": "ttm",
      "currency": "CNY",
      "net_income": 29534549.09,
      "outstanding_shares": 108472091.0,
      "total_assets": 1692744129.22,
      "total_liabilities": 164768642.67,
      "shareholders_equity": 1527284929.94,
      "gross_profit": 35450665.86,
      "revenue": 101152000.27
    },
    {
      "ticker": "301373",
      "report_period": "20231231",
      "period": "ttm",
      "currency": "CNY",
      "net_income": 124873687.63,
      "outstanding_shares": 108472091.0,
      "total_assets": 1688819110.47,
      "total_liabilities": 190428252.11,
      "shareholders_equity": 1497750380.84,
      "gross_profit": 150229316.2,
      "revenue": 465896868.3
    }
  ]
}