{
  "financial_metrics": [
    {
      "ticker": "002470",
      "report_period": "20250930",
      "period": "ttm",
      "currency": "CNY",
      "market_cap": 5651967716.0,
      "enterprise_value": null,
      "price_to_earnings_ratio": null,
      "price_to_book_ratio": null,
      "price_to_sales_ratio": null,
      "enterprise_value_to_ebitda_ratio": null,
      "enterprise_value_to_revenue_ratio": null,
      "free_cash_flow_yield": null,
      "peg_ratio": null,
      "gross_margin": 11.9945,
      "operating_margin": 0.5142,
      "net_margin": -0.3921,
      "return_on_equity": -1.4343,
      "return_on_assets": 0.7216,
      "return_on_invested_capital": null,
      "asset_turnover": 0.6435,
      "inventory_turnover": null,
      "receivables_turnover": null,
      "days_sales_outstanding": null,
      "operating_cycle": null,
      "working_capital_turnover": null,
      "current_ratio": 0.7926,
      "quick_ratio": 0.4,
      "cash_ratio": 0.3232,
      "operating_cash_flow_ratio": null,
      "debt_to_equity": 4.469,
      "debt_to_assets": 81.715,
      "interest_coverage": null,
      "revenue_growth": 0.386982,
      "earnings_growth": -1.16363,
      "book_value_growth": null,
      "earnings_per_share_growth": -1.164234,
      "free_cash_flow_growth": null,
      "operating_income_growth": -0.781809,
      "ebitda_growth": null,
      "payout_ratio": null,
      "earnings_per_share": -0.009,
      "book_value_per_share": 0.6253,
      "free_cash_flow_per_share": null
    },
    {
      "ticker": "002470",
      "report_period": "20250630",
      "period": "ttm",
      "currency": "CNY",
      "market_cap": 5684827994.0,
      "enterprise_value": null,
      "price_to_earnings_ratio": null,
      "price_to_book_ratio": null,
      "price_to_sales_ratio": null,
      "enterprise_value_to_ebitda_ratio": null,
      "enterprise_value_to_revenue_ratio": null,
      "free_cash_flow_yield": null,
      "peg_ratio": null,
      "gross_margin": 11.8103,
      "operating_margin": -0.3453,
      "net_margin": -1.5894,
      "return_on_equity": -3.8638,
      "return_on_assets": 0.0353,
      "return_on_invested_capital": null,
      "asset_turnover": 0.4207,
      "inventory_turnover": null,
      "receivables_turnover": null,
      "days_sales_outstanding": null,
      "operating_cycle": null,
      "working_capital_turnover": null,
      "current_ratio": 0.787,
      "quick_ratio": 0.3779,
      "cash_ratio": 0.2954,
      "operating_cash_flow_ratio": null,
      "debt_to_equity": 4.6463,
      "debt_to_assets": 82.2892,
      "interest_coverage": null,
      "revenue_growth": -0.063298,
      "earnings_growth": -1.4650040000000002,
      "book_value_growth": null,
      "earnings_per_share_growth": -1.463938,
      "free_cash_flow_growth": null,
      "operating_income_growth": -1.093526,
      "ebitda_growth": null,
      "payout_ratio": null,
      "earnings_per_share": -0.0238,
      "book_value_per_share": 0.6081,
      "free_cash_flow_per_share": null
    },
    {
      "ticker": "002470",
      "report_period": "20250331",
      "period": "ttm",
      "currency": "CNY",
      "market_cap": 5849129381.0,
      "enterprise_value": null,
      "price_to_earnings_ratio": null,
      "price_to_book_ratio": null,
      "price_to_sales_ratio": null,
      "enterprise_value_to_ebitda_ratio": null,
      "enterprise_value_to_revenue_ratio": null,
      "free_cash_flow_yield": null,
      "peg_ratio": null,
      "gross_margin": 11.9308,
      "operating_margin": 1.0175,
      "net_margin": 0.4177,
      "return_on_equity": 0.4271,
      "return_on_assets": 0.4635,
      "return_on_invested_capital": null,
      "asset_turnover": 0.2077,
      "inventory_turnover": null,
      "receivables_turnover": null,
      "days_sales_outstanding": null,
      "operating_cycle": null,
      "working_capital_turnover": null,
      "current_ratio": 0.7723,
      "quick_ratio": 0.3868,
      "cash_ratio": 0.2649,
      "operating_cash_flow_ratio": null,
      "debt_to_equity": 4.37,
      "debt_to_assets": 81.3779,
      "interest_coverage": null,
      "revenue_growth": 0.196719,
      "earnings_growth": -0.672585,
      "book_value_growth": null,
      "earnings_per_share_growth": -0.670732,
      "free_cash_flow_growth": null,
      "operating_income_growth": 0.131729,
      "ebitda_growth": null,
      "payout_ratio": null,
      "earnings_per_share": 0.0027,
      "book_value_per_share": 0.6291,
      "free_cash_flow_per_share": null
    },
    {
      "ticker": "002470",
      "report_period": "20241231",
      "period": "ttm",
      "currency": "CNY",
      "market_cap": 6440614374.000001,
      "enterprise_value": null,
      "price_to_earnings_ratio": null,
      "price_to_book_ratio": null,
      "price_to_sales_ratio": null,
      "enterprise_value_to_ebitda_ratio": null,
      "enterprise_value_to_revenue_ratio": null,
      "free_cash_flow_yield": null,
      "peg_ratio": null,
      "gross_margin": 12.3885,
      "operating_margin": 0.252,
      "net_margin": 0.722,
      "return_on_equity": 2.9344,
      "return_on_assets": 2.27,
      "return_on_invested_capital": null,
      "asset_turnover": 0.7305,
      "inventory_turnover": null,
      "receivables_turnover": null,
      "days_sales_outstanding": null,
      "operating_cycle": null,
      "working_capital_turnover": null,
      "current_ratio": 0.7208,
      "quick_ratio": 0.3269,
      "cash_ratio": 0.2549,
      "operating_cash_flow_ratio": null,
      "debt_to_equity": 4.1574,
      "debt_to_assets": 80.6104,
      "interest_coverage": null,
      "revenue_growth": 0.075797,
      "earnings_growth": 1.061455,
      "book_value_growth": null,
      "earnings_per_share_growth": 1.06157,
      "free_cash_flow_growth": null,
      "operating_income_growth": 1.021649,
      "ebitda_growth": null,
      "payout_ratio": null,
      "earnings_per_share": 0.0182,
      "book_value_per_share": 0.6255,
      "free_cash_flow_per_share": null
    },
    {
      "ticker": "002470",
      "report_period": "20240930",
      "period": "ttm",
      "currency": "CNY",
      "market_cap": 5454806052.0,
      "enterprise_value": null,
      "price_to_earnings_ratio": null,
      "price_to_book_ratio": null,
      "price_to_sales_ratio": null,
      "enterprise_value_to_ebitda_ratio": null,
      "enterprise_value_to_revenue_ratio": null,
      "free_cash_flow_yield": null,
      "peg_ratio": null,
      "gross_margin": 11.6831,
      "operating_margin": 2.6968,
      "net_margin": 2.8522,
      "return_on_equity": 8.54,
      "return_on_assets": 2.763,
      "return_on_invested_capital": null,
      "asset_turnover": 0.5594,
      "inventory_turnover": null,
      "receivables_turnover": null,
      "days_sales_outstanding": null,
      "operating_cycle": null,
      "working_capital_turnover": null,
      "current_ratio": 0.6805,
      "quick_ratio": 0.3114,
      "cash_ratio": 0.2301,
      "operating_cash_flow_ratio": null,
      "debt_to_equity": 3.8724,
      "debt_to_assets": 79.4761,
      "interest_coverage": null,
      "revenue_growth": -0.13248100000000002,
      "earnings_growth": 1.387202,
      "book_value_growth": null,
      "earnings_per_share_growth": 1.3870060000000002,
      "free_cash_flow_growth": null,
      "operating_income_growth": 1.3799940000000002,
      "ebitda_growth": null,
      "payout_ratio": null,
      "earnings_per_share": 0.0548,
      "book_value_per_share": 0.6714,
      "free_cash_flow_per_share": null
    },
    {
      "ticker": "002470",
      "report_period": "20240630",
      "period": "ttm",
      "currency": "CNY",
      "market_cap": null,
      "enterprise_value": null,
      "price_to_earnings_ratio": null,
      "price_to_book_ratio": null,
      "price_to_sales_ratio": null,
      "enterprise_value_to_ebitda_ratio": null,
      "enterprise_value_to_revenue_ratio": null,
      "free_cash_flow_yield": null,
      "peg_ratio": null,
      "gross_margin": 11.4964,
      "operating_margin": 3.8695,
      "net_margin": 3.7476,
      "return_on_equity": 8.0197,
      "return_on_assets": 2.2849,
      "return_on_invested_capital": null,
      "asset_turnover": 0.3946,
      "inventory_turnover": null,
      "receivables_turnover": null,
      "days_sales_outstanding": null,
      "operating_cycle": null,
      "working_capital_turnover": null,
      "current_ratio": 0.6947,
      "quick_ratio": 0.3468,
      "cash_ratio": 0.2661,
      "operating_cash_flow_ratio": null,
      "debt_to_equity": 4.0599,
      "debt_to_assets": 80.2368,
      "interest_coverage": null,
      "revenue_growth": 0.34633800000000003,
      "earnings_growth": 2.112198,
      "book_value_growth": null,
      "earnings_per_share_growth": 2.1127979999999997,
      "free_cash_flow_growth": null,
      "operating_income_growth": 2.276167,
      "ebitda_growth": null,
      "payout_ratio": null,
      "earnings_per_share": 0.0513,
      "book_value_per_share": 0.6657,
      "free_cash_flow_per_share": null
    },
    {
      "ticker": "002470",
      "report_period": "20240630",
      "period": "ttm",
      "currency": "CNY",
      "market_cap": null,
      "enterprise_value": null,
      "price_to_earnings_ratio": null,
      "price_to_book_ratio": null,
      "price_to_sales_ratio": null,
      "enterprise_value_to_ebitda_ratio": null,
      "enterprise_value_to_revenue_ratio": null,
      "free_cash_flow_yield": null,
      "peg_ratio": null,
      "gross_margin": 11.4964,
      "operating_margin": 3.8695,
      "net_margin": 3.7476,
      "return_on_equity": 8.0197,
      "return_on_assets": 2.2849,
      "return_on_invested_capital": null,
      "asset_turnover": 0.3946,
      "inventory_turnover": null,
      "receivables_turnover": null,
      "days_sales_outstanding": null,
      "operating_cycle": null,
      "working_capital_turnover": null,
      "current_ratio": 0.6947,
      "quick_ratio": 0.3468,
      "cash_ratio": 0.2661,
      "operating_cash_flow_ratio": null,
      "debt_to_equity": 4.0599,
      "debt_to_assets": 80.2368,
      "interest_coverage": null,
      "revenue_growth": 0.34633800000000003,
      "earnings_growth": 2.112198,
      "book_value_growth": null,
      "earnings_per_share_growth": 2.1127979999999997,
      "free_cash_flow_growth": null,
      "operating_income_growth": 2.276167,
      "ebitda_growth": null,
      "payout_ratio": null,
      "earnings_per_share": 0.0513,
      "book_value_per_share": 0.6657,
      "free_cash_flow_per_share": null
    },
    {
      "ticker": "002470",
      "report_period": "20240331",
      "period": "ttm",
      "currency": "CNY",
      "market_cap": null,
      "enterprise_value": null,
      "price_to_earnings_ratio": null,
      "price_to_book_ratio": null,
      "price_to_sales_ratio": null,
      "enterprise_value_to_ebitda_ratio": null,
      "enterprise_value_to_revenue_ratio": null,
      "free_cash_flow_yield": null,
      "peg_ratio": null,
      "gross_margin": 14.1791,
      "operating_margin": 1.0759,
      "net_margin": 1.448,
      "return_on_equity": 1.3252,
      "return_on_assets": 0.739,
      "return_on_invested_capital": null,
      "asset_turnover": 0.1687,
      "inventory_turnover": null,
      "receivables_turnover": null,
      "days_sales_outstanding": null,
      "operating_cycle": null,
      "working_capital_turnover": null,
      "current_ratio": 0.67,
      "quick_ratio": 0.3397,
      "cash_ratio": 0.2636,
      "operating_cash_flow_ratio": null,
      "debt_to_equity": 4.4261,
      "debt_to_assets": 81.5704,
      "interest_coverage": null,
      "revenue_growth": -0.277322,
      "earnings_growth": 1.667872,
      "book_value_growth": null,
      "earnings_per_share_growth": 1.666667,
      "free_cash_flow_growth": null,
      "operating_income_growth": 1.8851920000000002,
      "ebitda_growth": null,
      "payout_ratio": null,
      "earnings_per_share": 0.0082,
      "book_value_per_share": 0.6224,
      "free_cash_flow_per_share": null
    },
    {
      "ticker": "002470",
      "report_period": "20231231",
      "period": "ttm",
      "currency": "CNY",
      "market_cap": null,
      "enterprise_value": null,
      "price_to_earnings_ratio": null,
      "price_to_book_ratio": null,
      "price_to_sales_ratio": null,
      "enterprise_value_to_ebitda_ratio": null,
      "enterprise_value_to_revenue_ratio": null,
      "free_cash_flow_yield": null,
      "peg_ratio": null,
      "gross_margin": 8.2769,
      "operating_margin": -11.3395,
      "net_margin": -11.4596,
      "return_on_equity": -39.034,
      "return_on_assets": -5.9567,
      "return_on_invested_capital": null,
      "asset_turnover": 0.6774,
      "inventory_turnover": null,
      "receivables_turnover": null,
      "days_sales_outstanding": null,
      "operating_cycle": null,
      "working_capital_turnover": null,
      "current_ratio": 0.6935,
      "quick_ratio": 0.3501,
      "cash_ratio": 0.2691,
      "operating_cash_flow_ratio": null,
      "debt_to_equity": 4.6446,
      "debt_to_assets": 82.284,
      "interest_coverage": null,
      "revenue_growth": -0.18912199999999998,
      "earnings_growth": 0.011323000000000001,
      "book_value_growth": null,
      "earnings_per_share_growth": 0.011040000000000001,
      "free_cash_flow_growth": null,
      "operating_income_growth": -0.188746,
      "ebitda_growth": null,
      "payout_ratio": null,
      "earnings_per_share": -0.2956,
      "book_value_per_share": 0.6124,
      "free_cash_flow_per_share": null
    },
    {
      "ticker": "002470",
      "report_period": "20230930",
      "period": "ttm",
      "currency": "CNY",
      "market_cap": null,
      "enterprise_value": null,
      "price_to_earnings_ratio": null,
      "price_to_book_ratio": null,
      "price_to_sales_ratio": null,
      "enterprise_value_to_ebitda_ratio": null,
      "enterprise_value_to_revenue_ratio": null,
      "free_cash_flow_yield": null,
      "peg_ratio": null,
      "gross_margin": 7.6302,
      "operating_margin": -6.7217,
      "net_margin": -6.901,
      "return_on_equity": -17.0835,
      "return_on_assets": -1.9292,
      "return_on_invested_capital": null,
      "asset_turnover": 0.514,
      "inventory_turnover": null,
      "receivables_turnover": null,
      "days_sales_outstanding": null,
      "operating_cycle": null,
      "working_capital_turnover": null,
      "current_ratio": 0.7072,
      "quick_ratio": 0.439,
      "cash_ratio": 0.3799,
      "operating_cash_flow_ratio": null,
      "debt_to_equity": 3.9946,
      "debt_to_assets": 79.9784,
      "interest_coverage": null,
      "revenue_growth": 0.145631,
      "earnings_growth": 0.307675,
      "book_value_growth": null,
      "earnings_per_share_growth": 0.307579,
      "free_cash_flow_growth": null,
      "operating_income_growth": 0.12602,
      "ebitda_growth": null,
      "payout_ratio": null,
      "earnings_per_share": -0.1416,
      "book_value_per_share": 0.7556,
      "free_cash_flow_per_share": null
    }
  ],
  "line_items": [
    {
      "ticker": "002470",
      "report_period": "20250930",
      "period": "ttm",
      "currency": "CNY",
      "capital_expenditure": 148035501.19,
      "net_income": -29476396.21,
      "outstanding_shares": 3286027742.0,
      "total_assets": 11707982037.25,
      "total_liabilities": 9567180565.58,
      "shareholders_equity": 2054821294.35,
      "dividends_and_other_cash_distributions": 64348403.9,
      "gross_profit": -654801.89,
      "revenue": 7319201309.42
    },
    {
      "ticker": "002470",
      "report_period": "20250630",
      "period": "ttm",
      "currency": "CNY",
      "capital_expenditure": 128689259.29,
      "depreciation_and_amortization": 242305995.16,
      "net_income": -78314444.98,
      "outstanding_shares": 3286027742.0,
      "total_assets": 11775343734.65,
      "total_liabilities": 9689833885.87,
      "shareholders_equity": 1998267940.17,
      "dividends_and_other_cash_distributions": 44269277.85,
      "gross_profit": -51099423.26,
      "revenue": 4798962798.82,
      "free_cash_flow": 249415013.85
    },
    {
      "ticker": "002470",
      "report_period": "20250331",
      "period": "ttm",
      "currency": "CNY",
      "capital_expenditure": 55418227.5,
      "net_income": 8803293.21,
      "outstanding_shares": 3286027742.0,
      "total_assets": 11563272852.74,
      "total_liabilities": 9409950066.54,
      "shareholders_equity": 2067117786.0,
      "dividends_and_other_cash_distributions": 23838359.08,
      "gross_profit": 24319373.16,
      "revenue": 2347531089.87,
      "free_cash_flow": -130362311.3613
    },
    {
      "ticker": "002470",
      "report_period": "20241231",
      "period": "ttm",
      "currency": "CNY",
      "capital_expenditure": 430059987.2,
      "depreciation_and_amortization": 569327543.93,
      "net_income": 59685334.17,
      "outstanding_shares": 3286027742.0,
      "total_assets": 11040445013.03,
      "total_liabilities": 8899745966.99,
      "shareholders_equity": 2055496766.94,
      "dividends_and_other_cash_distributions": 95266362.32,
      "gross_profit": 102129275.62,
      "revenue": 8328058513.21,
      "free_cash_flow": -53095903.1742
    },
    {
      "ticker": "002470",
      "report_period": "20240930",
      "period": "ttm",
      "currency": "CNY",
      "capital_expenditure": 267221704.82,
      "net_income": 180140291.61,
      "outstanding_shares": 3286027742.0,
      "total_assets": 11107037003.81,
      "total_liabilities": 8827441073.18,
      "shareholders_equity": 2206309313.18,
      "dividends_and_other_cash_distributions": 71135320.91,
      "gross_profit": 208429237.3,
      "revenue": 6395792186.36,
      "free_cash_flow": -204647521.6068
    },
    {
      "ticker": "002470",
      "report_period": "20240630",
      "period": "ttm",
      "currency": "CNY",
      "capital_expenditure": 127180454.32,
      "depreciation_and_amortization": 291623924.28,
      "net_income": 168416738.92,
      "outstanding_shares": 3286027742.0,
      "total_assets": 11444653549.75,
      "total_liabilities": 9182822461.27,
      "shareholders_equity": 2187646529.92,
      "dividends_and_other_cash_distributions": 47759557.68,
      "gross_profit": 197395342.36,
      "revenue": 4578725951.31,
      "free_cash_flow": 581784090.2213
    },
    {
      "ticker": "002470",
      "report_period": "20240630",
      "period": "ttm",
      "currency": "CNY",
      "capital_expenditure": 127180454.32,
      "depreciation_and_amortization": 291623924.28,
      "net_income": 168416738.92,
      "outstanding_shares": 3286027742.0,
      "total_assets": 11444653549.75,
      "total_liabilities": 9182822461.27,
      "shareholders_equity": 2187646529.92,
      "dividends_and_other_cash_distributions": 47759557.68,
      "gross_profit": 197395342.36,
      "revenue": 4578725951.31,
      "free_cash_flow": 581784090.2213
    },
    {
      "ticker": "002470",
      "report_period": "20240331",
      "period": "ttm",
      "currency": "CNY",
      "capital_expenditure": 42713949.83,
      "net_income": 26887276.49,
      "outstanding_shares": 3286027742.0,
      "total_assets": 11491461985.42,
      "total_liabilities": 9373636994.85,
      "shareholders_equity": 2045299345.77,
      "dividends_and_other_cash_distributions": 23979713.64,
      "issuance_or_purchase_of_equity_shares": 0.0,
      "gross_profit": 41116543.45,
      "revenue": 1961638767.04,
      "free_cash_flow": 23815968.66
    },
    {
      "ticker": "002470",
      "report_period": "20231231",
      "period": "ttm",
      "currency": "CNY",
      "net_income": -971207098.07,
      "outstanding_shares": 3286027742.0,
      "total_assets": 11760358098.57,
      "total_liabilities": 9676897122.77,
      "shareholders_equity": 2012452325.06,
      "gross_profit": -961271282.79,
      "revenue": 8548940363.92
    },
    {
      "ticker": "002470",
      "report_period": "20230930",
      "period": "ttm",
      "currency": "CNY",
      "net_income": -465235456.73,
      "outstanding_shares": 3286027742.0,
      "total_assets": 12791181943.69,
      "total_liabilities": 10230176385.96,
      "shareholders_equity": 2482835342.58,
      "gross_profit": -441966503.06,
      "revenue": 6752814414.44
    }
  ]
}