{
  "financial_metrics": [
    {
      "ticker": "000826",
      "report_period": "20250930",
      "period": "ttm",
      "currency": "CNY",
      "market_cap": 3406594263.0,
      "enterprise_value": null,
      "price_to_earnings_ratio": null,
      "price_to_book_ratio": null,
      "price_to_sales_ratio": null,
      "enterprise_value_to_ebitda_ratio": null,
      "enterprise_value_to_revenue_ratio": null,
      "free_cash_flow_yield": null,
      "peg_ratio": null,
      "gross_margin": 23.2684,
      "operating_margin": -13.8709,
      "net_margin": -19.4444,
      "return_on_equity": -55.9177,
      "return_on_assets": -0.9679,
      "return_on_invested_capital": null,
      "asset_turnover": 0.1677,
      "inventory_turnover": null,
      "receivables_turnover": null,
      "days_sales_outstanding": null,
      "operating_cycle": null,
      "working_capital_turnover": null,
      "current_ratio": 0.6718,
      "quick_ratio": 0.6462,
      "cash_ratio": 0.5868,
      "operating_cash_flow_ratio": null,
      "debt_to_equity": 6.2293,
      "debt_to_assets": 86.1674,
      "interest_coverage": null,
      "revenue_growth": -0.106286,
      "earnings_growth": 0.38595399999999996,
      "book_value_growth": null,
      "earnings_per_share_growth": 0.35781999999999997,
      "free_cash_flow_growth": null,
      "operating_income_growth": 0.17494099999999999,
      "ebitda_growth": null,
      "payout_ratio": null,
      "earnings_per_share": -0.542,
      "book_value_per_share": 0.0294,
      "free_cash_flow_per_share": null
    },
    {
      "ticker": "000826",
      "report_period": "20250630",
      "period": "ttm",
      "currency": "CNY",
      "market_cap": 2807945899.0,
      "enterprise_value": null,
      "price_to_earnings_ratio": null,
      "price_to_book_ratio": null,
      "price_to_sales_ratio": null,
      "enterprise_value_to_ebitda_ratio": null,
      "enterprise_value_to_revenue_ratio": null,
      "free_cash_flow_yield": null,
      "peg_ratio": null,
      "gross_margin": 23.6242,
      "operating_margin": -16.5011,
      "net_margin": -22.4377,
      "return_on_equity": -24.9549,
      "return_on_assets": -0.9849,
      "return_on_invested_capital": null,
      "asset_turnover": 0.1121,
      "inventory_turnover": null,
      "receivables_turnover": null,
      "days_sales_outstanding": null,
      "operating_cycle": null,
      "working_capital_turnover": null,
      "current_ratio": 0.673,
      "quick_ratio": 0.6497,
      "cash_ratio": 0.5933,
      "operating_cash_flow_ratio": null,
      "debt_to_equity": 3.429,
      "debt_to_assets": 77.4214,
      "interest_coverage": null,
      "revenue_growth": -0.119847,
      "earnings_growth": -1.39018,
      "book_value_growth": null,
      "earnings_per_share_growth": -1.086735,
      "free_cash_flow_growth": null,
      "operating_income_growth": -4.443353,
      "ebitda_growth": null,
      "payout_ratio": null,
      "earnings_per_share": -0.409,
      "book_value_per_share": 0.2093,
      "free_cash_flow_per_share": null
    },
    {
      "ticker": "000826",
      "report_period": "20250331",
      "period": "ttm",
      "currency": "CNY",
      "market_cap": 2551382314.0,
      "enterprise_value": null,
      "price_to_earnings_ratio": null,
      "price_to_book_ratio": null,
      "price_to_sales_ratio": null,
      "enterprise_value_to_ebitda_ratio": null,
      "enterprise_value_to_revenue_ratio": null,
      "free_cash_flow_yield": null,
      "peg_ratio": null,
      "gross_margin": 22.725,
      "operating_margin": -4.0273,
      "net_margin": -9.7588,
      "return_on_equity": -5.7845,
      "return_on_assets": 0.2044,
      "return_on_invested_capital": null,
      "asset_turnover": 0.0541,
      "inventory_turnover": null,
      "receivables_turnover": null,
      "days_sales_outstanding": null,
      "operating_cycle": null,
      "working_capital_turnover": null,
      "current_ratio": 0.6454,
      "quick_ratio": 0.622,
      "cash_ratio": 0.5624,
      "operating_cash_flow_ratio": null,
      "debt_to_equity": 3.3561,
      "debt_to_assets": 77.0436,
      "interest_coverage": null,
      "revenue_growth": -0.090436,
      "earnings_growth": -0.570029,
      "book_value_growth": null,
      "earnings_per_share_growth": -0.9322029999999999,
      "free_cash_flow_growth": null,
      "operating_income_growth": -0.8194830000000001,
      "ebitda_growth": null,
      "payout_ratio": null,
      "earnings_per_share": -0.114,
      "book_value_per_share": 0.4838,
      "free_cash_flow_per_share": null
    },
    {
      "ticker": "000826",
      "report_period": "20241231",
      "period": "ttm",
      "currency": "CNY",
      "market_cap": 2850706496.0,
      "enterprise_value": null,
      "price_to_earnings_ratio": null,
      "price_to_book_ratio": null,
      "price_to_sales_ratio": null,
      "enterprise_value_to_ebitda_ratio": null,
      "enterprise_value_to_revenue_ratio": null,
      "free_cash_flow_yield": null,
      "peg_ratio": null,
      "gross_margin": 23.7748,
      "operating_margin": -38.7402,
      "net_margin": -58.7797,
      "return_on_equity": -74.2553,
      "return_on_assets": -9.3946,
      "return_on_invested_capital": null,
      "asset_turnover": 0.2356,
      "inventory_turnover": null,
      "receivables_turnover": null,
      "days_sales_outstanding": null,
      "operating_cycle": null,
      "working_capital_turnover": null,
      "current_ratio": 0.6508,
      "quick_ratio": 0.627,
      "cash_ratio": 0.5668,
      "operating_cash_flow_ratio": null,
      "debt_to_equity": 3.2319,
      "debt_to_assets": 76.3702,
      "interest_coverage": null,
      "revenue_growth": -0.025737,
      "earnings_growth": -0.9447490000000001,
      "book_value_growth": null,
      "earnings_per_share_growth": -0.879528,
      "free_cash_flow_growth": null,
      "operating_income_growth": -0.407368,
      "ebitda_growth": null,
      "payout_ratio": null,
      "earnings_per_share": -2.231,
      "book_value_per_share": 0.6357,
      "free_cash_flow_per_share": null
    },
    {
      "ticker": "000826",
      "report_period": "20240930",
      "period": "ttm",
      "currency": "CNY",
      "market_cap": 2864960028.0,
      "enterprise_value": null,
      "price_to_earnings_ratio": null,
      "price_to_book_ratio": null,
      "price_to_sales_ratio": null,
      "enterprise_value_to_ebitda_ratio": null,
      "enterprise_value_to_revenue_ratio": null,
      "free_cash_flow_yield": null,
      "peg_ratio": null,
      "gross_margin": 26.1506,
      "operating_margin": -15.0353,
      "net_margin": -27.3939,
      "return_on_equity": -21.7409,
      "return_on_assets": -2.3372,
      "return_on_invested_capital": null,
      "asset_turnover": 0.1593,
      "inventory_turnover": null,
      "receivables_turnover": null,
      "days_sales_outstanding": null,
      "operating_cycle": null,
      "working_capital_turnover": null,
      "current_ratio": 0.7159,
      "quick_ratio": 0.6784,
      "cash_ratio": 0.6101,
      "operating_cash_flow_ratio": null,
      "debt_to_equity": 2.2129,
      "debt_to_assets": 68.8755,
      "interest_coverage": null,
      "revenue_growth": -0.053468,
      "earnings_growth": -3.379039,
      "book_value_growth": null,
      "earnings_per_share_growth": -2.502075,
      "free_cash_flow_growth": null,
      "operating_income_growth": -11.544941,
      "ebitda_growth": null,
      "payout_ratio": null,
      "earnings_per_share": -0.844,
      "book_value_per_share": 2.0387,
      "free_cash_flow_per_share": null
    },
    {
      "ticker": "000826",
      "report_period": "20240630",
      "period": "ttm",
      "currency": "CNY",
      "market_cap": null,
      "enterprise_value": null,
      "price_to_earnings_ratio": null,
      "price_to_book_ratio": null,
      "price_to_sales_ratio": null,
      "enterprise_value_to_ebitda_ratio": null,
      "enterprise_value_to_revenue_ratio": null,
      "free_cash_flow_yield": null,
      "peg_ratio": null,
      "gross_margin": 26.3179,
      "operating_margin": -2.7119,
      "net_margin": -5.9316,
      "return_on_equity": -3.8589,
      "return_on_assets": 0.7936,
      "return_on_invested_capital": null,
      "asset_turnover": 0.1058,
      "inventory_turnover": null,
      "receivables_turnover": null,
      "days_sales_outstanding": null,
      "operating_cycle": null,
      "working_capital_turnover": null,
      "current_ratio": 0.7494,
      "quick_ratio": 0.7096,
      "cash_ratio": 0.6365,
      "operating_cash_flow_ratio": null,
      "debt_to_equity": 1.8747,
      "debt_to_assets": 65.2134,
      "interest_coverage": null,
      "revenue_growth": -0.012253,
      "earnings_growth": -0.37213999999999997,
      "book_value_growth": null,
      "earnings_per_share_growth": -0.272727,
      "free_cash_flow_growth": null,
      "operating_income_growth": -2.220629,
      "ebitda_growth": null,
      "payout_ratio": null,
      "earnings_per_share": -0.196,
      "book_value_per_share": 2.8216,
      "free_cash_flow_per_share": null
    },
    {
      "ticker": "000826",
      "report_period": "20240331",
      "period": "ttm",
      "currency": "CNY",
      "market_cap": null,
      "enterprise_value": null,
      "price_to_earnings_ratio": null,
      "price_to_book_ratio": null,
      "price_to_sales_ratio": null,
      "enterprise_value_to_ebitda_ratio": null,
      "enterprise_value_to_revenue_ratio": null,
      "free_cash_flow_yield": null,
      "peg_ratio": null,
      "gross_margin": 24.792,
      "operating_margin": -2.0133,
      "net_margin": -4.6997,
      "return_on_equity": -1.4696,
      "return_on_assets": 0.3671,
      "return_on_invested_capital": null,
      "asset_turnover": 0.0518,
      "inventory_turnover": null,
      "receivables_turnover": null,
      "days_sales_outstanding": null,
      "operating_cycle": null,
      "working_capital_turnover": null,
      "current_ratio": 0.8401,
      "quick_ratio": 0.7943,
      "cash_ratio": 0.7121,
      "operating_cash_flow_ratio": null,
      "debt_to_equity": 1.844,
      "debt_to_assets": 64.8378,
      "interest_coverage": null,
      "revenue_growth": -0.026495,
      "earnings_growth": -0.09024499999999999,
      "book_value_growth": null,
      "earnings_per_share_growth": 0.21333300000000002,
      "free_cash_flow_growth": null,
      "operating_income_growth": -0.394692,
      "ebitda_growth": null,
      "payout_ratio": null,
      "earnings_per_share": -0.059,
      "book_value_per_share": 2.9254,
      "free_cash_flow_per_share": null
    },
    {
      "ticker": "000826",
      "report_period": "20231231",
      "period": "ttm",
      "currency": "CNY",
      "market_cap": null,
      "enterprise_value": null,
      "price_to_earnings_ratio": null,
      "price_to_book_ratio": null,
      "price_to_sales_ratio": null,
      "enterprise_value_to_ebitda_ratio": null,
      "enterprise_value_to_revenue_ratio": null,
      "free_cash_flow_yield": null,
      "peg_ratio": null,
      "gross_margin": 18.6806,
      "operating_margin": -26.7224,
      "net_margin": -29.7371,
      "return_on_equity": -23.5505,
      "return_on_assets": -3.8104,
      "return_on_invested_capital": null,
      "asset_turnover": 0.2142,
      "inventory_turnover": null,
      "receivables_turnover": null,
      "days_sales_outstanding": null,
      "operating_cycle": null,
      "working_capital_turnover": null,
      "current_ratio": 0.8524,
      "quick_ratio": 0.8067,
      "cash_ratio": 0.7215,
      "operating_cash_flow_ratio": null,
      "debt_to_equity": 1.8197,
      "debt_to_assets": 64.5351,
      "interest_coverage": null,
      "revenue_growth": -0.11031200000000001,
      "earnings_growth": -0.6314379999999999,
      "book_value_growth": null,
      "earnings_per_share_growth": -0.565963,
      "free_cash_flow_growth": null,
      "operating_income_growth": -2.19526,
      "ebitda_growth": null,
      "payout_ratio": null,
      "earnings_per_share": -1.187,
      "book_value_per_share": 3.0435,
      "free_cash_flow_per_share": null
    },
    {
      "ticker": "000826",
      "report_period": "20230930",
      "period": "ttm",
      "currency": "CNY",
      "market_cap": null,
      "enterprise_value": null,
      "price_to_earnings_ratio": null,
      "price_to_book_ratio": null,
      "price_to_sales_ratio": null,
      "enterprise_value_to_ebitda_ratio": null,
      "enterprise_value_to_revenue_ratio": null,
      "free_cash_flow_yield": null,
      "peg_ratio": null,
      "gross_margin": 25.4327,
      "operating_margin": -1.1618,
      "net_margin": -3.7314,
      "return_on_equity": -3.4578,
      "return_on_assets": 1.2653,
      "return_on_invested_capital": null,
      "asset_turnover": 0.1473,
      "inventory_turnover": null,
      "receivables_turnover": null,
      "days_sales_outstanding": null,
      "operating_cycle": null,
      "working_capital_turnover": null,
      "current_ratio": 0.9828,
      "quick_ratio": 0.924,
      "cash_ratio": 0.8052,
      "operating_cash_flow_ratio": null,
      "debt_to_equity": 1.525,
      "debt_to_assets": 60.3955,
      "interest_coverage": null,
      "revenue_growth": -0.268158,
      "earnings_growth": -0.39858,
      "book_value_growth": null,
      "earnings_per_share_growth": -0.43452399999999997,
      "free_cash_flow_growth": null,
      "operating_income_growth": -1.301583,
      "ebitda_growth": null,
      "payout_ratio": null,
      "earnings_per_share": -0.241,
      "book_value_per_share": 3.9862,
      "free_cash_flow_per_share": null
    },
    {
      "ticker": "000826",
      "report_period": "20230630",
      "period": "ttm",
      "currency": "CNY",
      "market_cap": 4005242627.0,
      "enterprise_value": null,
      "price_to_earnings_ratio": null,
      "price_to_book_ratio": null,
      "price_to_sales_ratio": null,
      "enterprise_value_to_ebitda_ratio": null,
      "enterprise_value_to_revenue_ratio": null,
      "free_cash_flow_yield": null,
      "peg_ratio": null,
      "gross_margin": 25.2637,
      "operating_margin": -0.8258,
      "net_margin": -3.4246,
      "return_on_equity": -2.1584,
      "return_on_assets": 0.793,
      "return_on_invested_capital": null,
      "asset_turnover": 0.098,
      "inventory_turnover": null,
      "receivables_turnover": null,
      "days_sales_outstanding": null,
      "operating_cycle": null,
      "working_capital_turnover": null,
      "current_ratio": 0.9864,
      "quick_ratio": 0.927,
      "cash_ratio": 0.8114,
      "operating_cash_flow_ratio": null,
      "debt_to_equity": 1.512,
      "debt_to_assets": 60.1918,
      "interest_coverage": null,
      "revenue_growth": -0.320296,
      "earnings_growth": 0.327888,
      "book_value_growth": null,
      "earnings_per_share_growth": 0.206186,
      "free_cash_flow_growth": null,
      "operating_income_growth": 0.6888639999999999,
      "ebitda_growth": null,
      "payout_ratio": null,
      "earnings_per_share": -0.154,
      "book_value_per_share": 4.0524,
      "free_cash_flow_per_share": null
    }
  ],
  "line_items": [
    {
      "ticker": "000826",
      "report_period": "20250930",
      "period": "ttm",
      "currency": "CNY",
      "capital_expenditure": 100677780.72,
      "net_income": -683174909.23,
      "outstanding_shares": 1425353248.0,
      "total_assets": 18671750353.08,
      "total_liabilities": 16088959918.32,
      "shareholders_equity": 41910159.06,
      "dividends_and_other_cash_distributions": 149270916.91,
      "gross_profit": -563306131.95,
      "revenue": 3303777332.76,
      "free_cash_flow": -1456688277.63
    },
    {
      "ticker": "000826",
      "report_period": "20250630",
      "period": "ttm",
      "currency": "CNY",
      "capital_expenditure": 70109705.39,
      "depreciation_and_amortization": 137757070.92,
      "net_income": -523472868.25,
      "outstanding_shares": 1425353248.0,
      "total_assets": 19102835584.18,
      "total_liabilities": 14789678485.85,
      "shareholders_equity": 1793767825.59,
      "dividends_and_other_cash_distributions": 95346081.81,
      "gross_profit": -453596140.9,
      "revenue": 2231295460.0,
      "free_cash_flow": -31166032.97
    },
    {
      "ticker": "000826",
      "report_period": "20250331",
      "period": "ttm",
      "currency": "CNY",
      "capital_expenditure": 33344475.59,
      "net_income": -132659379.28,
      "outstanding_shares": 1425353248.0,
      "total_assets": 20481122818.23,
      "total_liabilities": 15779389363.47,
      "shareholders_equity": 2185154393.11,
      "dividends_and_other_cash_distributions": 43073302.18,
      "gross_profit": -83355365.55,
      "revenue": 1115290750.7
    },
    {
      "ticker": "000826",
      "report_period": "20241231",
      "period": "ttm",
      "currency": "CNY",
      "capital_expenditure": 182825194.74,
      "depreciation_and_amortization": 293990766.38,
      "net_income": -3057514008.93,
      "outstanding_shares": 1425353248.0,
      "total_assets": 20721867109.74,
      "total_liabilities": 15825323103.09,
      "shareholders_equity": 2401590666.68,
      "dividends_and_other_cash_distributions": 374937757.28,
      "issuance_or_purchase_of_equity_shares": 690000.0,
      "gross_profit": -2783839790.27,
      "revenue": 5244586481.99,
      "free_cash_flow": 2555262530.3
    },
    {
      "ticker": "000826",
      "report_period": "20240930",
      "period": "ttm",
      "currency": "CNY",
      "capital_expenditure": 88889893.15,
      "net_income": -1112578699.75,
      "outstanding_shares": 1425353248.0,
      "total_assets": 22566876316.46,
      "total_liabilities": 15543041935.68,
      "shareholders_equity": 4401345612.69,
      "dividends_and_other_cash_distributions": 273284371.37,
      "issuance_or_purchase_of_equity_shares": 200000.0,
      "gross_profit": -926933619.6,
      "revenue": 3694177273.71,
      "free_cash_flow": 505039581.6
    },
    {
      "ticker": "000826",
      "report_period": "20240630",
      "period": "ttm",
      "currency": "CNY",
      "capital_expenditure": 78034941.31,
      "depreciation_and_amortization": 149827644.91,
      "net_income": -219009788.59,
      "outstanding_shares": 1425353248.0,
      "total_assets": 23362583326.37,
      "total_liabilities": 15235541260.46,
      "shareholders_equity": 5517252593.93,
      "dividends_and_other_cash_distributions": 197643055.36,
      "issuance_or_purchase_of_equity_shares": 200000.0,
      "gross_profit": -76171014.2,
      "revenue": 2494149182.22,
      "free_cash_flow": 1526897036.69
    },
    {
      "ticker": "000826",
      "report_period": "20240331",
      "period": "ttm",
      "currency": "CNY",
      "capital_expenditure": 45984386.73,
      "net_income": -84494835.42,
      "outstanding_shares": 1425353248.0,
      "total_assets": 23542749145.38,
      "total_liabilities": 15264592870.63,
      "shareholders_equity": 5665224032.06,
      "dividends_and_other_cash_distributions": 115533230.99,
      "gross_profit": -27181101.83,
      "revenue": 1226182070.39,
      "free_cash_flow": -118085362.5
    },
    {
      "ticker": "000826",
      "report_period": "20231231",
      "period": "ttm",
      "currency": "CNY",
      "net_income": -1572189861.43,
      "outstanding_shares": 1425353248.0,
      "total_assets": 23805214178.57,
      "total_liabilities": 15362709240.22,
      "shareholders_equity": 5833546900.66,
      "gross_profit": -1513806292.99,
      "revenue": 5402431392.47
    },
    {
      "ticker": "000826",
      "report_period": "20230930",
      "period": "ttm",
      "currency": "CNY",
      "net_income": -254069144.6,
      "gross_profit": -59434132.06,
      "revenue": 3811065125.03
    },
    {
      "ticker": "000826",
      "report_period": "20230630",
      "period": "ttm",
      "currency": "CNY",
      "net_income": -170223458.14
    }
  ]
}