[
  {
    "open": 24.25,
    "close": 24.6,
    "high": 24.77,
    "low": 24.25,
    "volume": 7580,
    "time": "2025-06-03"
  },
  {
    "open": 24.6,
    "close": 24.59,
    "high": 24.82,
    "low": 24.42,
    "volume": 8858,
    "time": "2025-06-04"
  },
  {
    "open": 24.72,
    "close": 25.0,
    "high": 25.0,
    "low": 24.4,
    "volume": 12066,
    "time": "2025-06-05"
  },
  {
    "open": 24.9,
    "close": 24.99,
    "high": 25.31,
    "low": 24.85,
    "volume": 10530,
    "time": "2025-06-06"
  },
  {
    "open": 24.93,
    "close": 25.4,
    "high": 25.42,
    "low": 24.85,
    "volume": 13832,
    "time": "2025-06-09"
  },
  {
    "open": 25.3,
    "close": 25.05,
    "high": 25.63,
    "low": 24.83,
    "volume": 18348,
    "time": "2025-06-10"
  },
  {
    "open": 24.99,
    "close": 25.02,
    "high": 25.47,
    "low": 24.99,
    "volume": 12127,
    "time": "2025-06-11"
  },
  {
    "open": 25.13,
    "close": 25.46,
    "high": 25.58,
    "low": 24.9,
    "volume": 17873,
    "time": "2025-06-12"
  },
  {
    "open": 25.39,
    "close": 24.81,
    "high": 25.44,
    "low": 24.7,
    "volume": 17878,
    "time": "2025-06-13"
  },
  {
    "open": 25.13,
    "close": 25.1,
    "high": 25.25,
    "low": 24.79,
    "volume": 9640,
    "time": "2025-06-16"
  },
  {
    "open": 25.1,
    "close": 25.41,
    "high": 25.72,
    "low": 24.99,
    "volume": 18177,
    "time": "2025-06-17"
  },
  {
    "open": 25.41,
    "close": 25.67,
    "high": 25.71,
    "low": 25.18,
    "volume": 14311,
    "time": "2025-06-18"
  },
  {
    "open": 25.69,
    "close": 25.5,
    "high": 25.92,
    "low": 25.41,
    "volume": 14967,
    "time": "2025-06-19"
  },
  {
    "open": 25.55,
    "close": 25.32,
    "high": 25.75,
    "low": 25.14,
    "volume": 12404,
    "time": "2025-06-20"
  },
  {
    "open": 25.29,
    "close": 25.55,
    "high": 25.74,
    "low": 25.01,
    "volume": 17575,
    "time": "2025-06-23"
  },
  {
    "open": 25.57,
    "close": 26.0,
    "high": 26.04,
    "low": 25.57,
    "volume": 23862,
    "time": "2025-06-24"
  },
  {
    "open": 25.99,
    "close": 26.25,
    "high": 26.31,
    "low": 25.68,
    "volume": 24440,
    "time": "2025-06-25"
  },
  {
    "open": 26.21,
    "close": 26.18,
    "high": 26.68,
    "low": 26.0,
    "volume": 26096,
    "time": "2025-06-26"
  },
  {
    "open": 26.3,
    "close": 26.3,
    "high": 26.59,
    "low": 26.03,
    "volume": 20445,
    "time": "2025-06-27"
  },
  {
    "open": 26.39,
    "close": 26.41,
    "high": 26.56,
    "low": 26.25,
    "volume": 18884,
    "time": "2025-06-30"
  },
  {
    "open": 26.39,
    "close": 26.31,
    "high": 26.5,
    "low": 26.01,
    "volume": 17110,
    "time": "2025-07-01"
  },
  {
    "open": 26.17,
    "close": 26.18,
    "high": 26.21,
    "low": 25.85,
    "volume": 15100,
    "time": "2025-07-02"
  },
  {
    "open": 26.19,
    "close": 26.68,
    "high": 26.9,
    "low": 26.17,
    "volume": 23597,
    "time": "2025-07-03"
  },
  {
    "open": 26.68,
    "close": 26.18,
    "high": 26.82,
    "low": 26.13,
    "volume": 16792,
    "time": "2025-07-04"
  },
  {
    "open": 26.26,
    "close": 26.12,
    "high": 26.45,
    "low": 25.94,
    "volume": 12962,
    "time": "2025-07-07"
  },
  {
    "open": 26.09,
    "close": 26.49,
    "high": 26.7,
    "low": 25.94,
    "volume": 20722,
    "time": "2025-07-08"
  },
  {
    "open": 26.49,
    "close": 26.4,
    "high": 27.11,
    "low": 26.3,
    "volume": 27268,
    "time": "2025-07-09"
  },
  {
    "open": 26.4,
    "close": 26.02,
    "high": 26.49,
    "low": 25.85,
    "volume": 19032,
    "time": "2025-07-10"
  },
  {
    "open": 26.04,
    "close": 26.0,
    "high": 26.21,
    "low": 25.8,
    "volume": 15220,
    "time": "2025-07-11"
  },
  {
    "open": 26.18,
    "close": 26.22,
    "high": 26.25,
    "low": 25.85,
    "volume": 12650,
    "time": "2025-07-14"
  },
  {
    "open": 26.29,
    "close": 26.18,
    "high": 26.44,
    "low": 25.8,
    "volume": 15203,
    "time": "2025-07-15"
  },
  {
    "open": 26.18,
    "close": 26.08,
    "high": 26.4,
    "low": 26.01,
    "volume": 12394,
    "time": "2025-07-16"
  },
  {
    "open": 26.33,
    "close": 26.46,
    "high": 26.7,
    "low": 25.91,
    "volume": 25705,
    "time": "2025-07-17"
  },
  {
    "open": 26.46,
    "close": 26.6,
    "high": 26.7,
    "low": 26.24,
    "volume": 19898,
    "time": "2025-07-18"
  },
  {
    "open": 26.62,
    "close": 27.76,
    "high": 28.14,
    "low": 26.51,
    "volume": 48052,
    "time": "2025-07-21"
  },
  {
    "open": 27.76,
    "close": 27.91,
    "high": 28.76,
    "low": 27.57,
    "volume": 40273,
    "time": "2025-07-22"
  },
  {
    "open": 27.9,
    "close": 28.18,
    "high": 28.43,
    "low": 27.57,
    "volume": 28810,
    "time": "2025-07-23"
  },
  {
    "open": 28.18,
    "close": 28.4,
    "high": 28.88,
    "low": 28.0,
    "volume": 35607,
    "time": "2025-07-24"
  },
  {
    "open": 28.42,
    "close": 29.64,
    "high": 29.98,
    "low": 28.42,
    "volume": 63476,
    "time": "2025-07-25"
  },
  {
    "open": 29.5,
    "close": 28.97,
    "high": 29.82,
    "low": 28.88,
    "volume": 41939,
    "time": "2025-07-28"
  },
  {
    "open": 28.94,
    "close": 29.14,
    "high": 29.44,
    "low": 28.58,
    "volume": 36619,
    "time": "2025-07-29"
  },
  {
    "open": 29.0,
    "close": 29.36,
    "high": 29.44,
    "low": 28.76,
    "volume": 39993,
    "time": "2025-07-30"
  },
  {
    "open": 29.3,
    "close": 29.2,
    "high": 29.65,
    "low": 29.12,
    "volume": 31511,
    "time": "2025-07-31"
  },
  {
    "open": 29.3,
    "close": 29.53,
    "high": 29.6,
    "low": 29.17,
    "volume": 27477,
    "time": "2025-08-01"
  },
  {
    "open": 29.34,
    "close": 29.82,
    "high": 30.21,
    "low": 29.34,
    "volume": 26897,
    "time": "2025-08-04"
  },
  {
    "open": 29.84,
    "close": 29.43,
    "high": 30.51,
    "low": 29.36,
    "volume": 37842,
    "time": "2025-08-05"
  },
  {
    "open": 29.11,
    "close": 30.27,
    "high": 31.0,
    "low": 29.11,
    "volume": 76104,
    "time": "2025-08-06"
  },
  {
    "open": 30.19,
    "close": 29.94,
    "high": 30.62,
    "low": 29.8,
    "volume": 33914,
    "time": "2025-08-07"
  },
  {
    "open": 29.8,
    "close": 29.2,
    "high": 29.94,
    "low": 29.16,
    "volume": 32990,
    "time": "2025-08-08"
  },
  {
    "open": 29.2,
    "close": 30.3,
    "high": 30.49,
    "low": 29.11,
    "volume": 39831,
    "time": "2025-08-11"
  },
  {
    "open": 30.39,
    "close": 30.79,
    "high": 30.89,
    "low": 29.97,
    "volume": 32691,
    "time": "2025-08-12"
  },
  {
    "open": 30.8,
    "close": 30.7,
    "high": 31.18,
    "low": 30.45,
    "volume": 28936,
    "time": "2025-08-13"
  },
  {
    "open": 30.8,
    "close": 30.55,
    "high": 31.66,
    "low": 30.45,
    "volume": 40404,
    "time": "2025-08-14"
  },
  {
    "open": 30.45,
    "close": 31.22,
    "high": 31.69,
    "low": 30.2,
    "volume": 40308,
    "time": "2025-08-15"
  },
  {
    "open": 31.41,
    "close": 33.16,
    "high": 33.56,
    "low": 31.01,
    "volume": 71091,
    "time": "2025-08-18"
  },
  {
    "open": 33.22,
    "close": 33.69,
    "high": 34.19,
    "low": 32.9,
    "volume": 53262,
    "time": "2025-08-19"
  },
  {
    "open": 33.49,
    "close": 34.45,
    "high": 34.8,
    "low": 32.84,
    "volume": 52902,
    "time": "2025-08-20"
  },
  {
    "open": 34.51,
    "close": 33.92,
    "high": 34.91,
    "low": 33.4,
    "volume": 45258,
    "time": "2025-08-21"
  },
  {
    "open": 33.7,
    "close": 33.44,
    "high": 33.8,
    "low": 33.03,
    "volume": 46061,
    "time": "2025-08-22"
  },
  {
    "open": 33.49,
    "close": 33.25,
    "high": 34.42,
    "low": 32.69,
    "volume": 74735,
    "time": "2025-08-25"
  },
  {
    "open": 33.88,
    "close": 34.94,
    "high": 36.42,
    "low": 33.4,
    "volume": 106422,
    "time": "2025-08-26"
  },
  {
    "open": 35.05,
    "close": 34.42,
    "high": 36.15,
    "low": 34.38,
    "volume": 78130,
    "time": "2025-08-27"
  },
  {
    "open": 34.23,
    "close": 35.16,
    "high": 35.5,
    "low": 34.23,
    "volume": 58049,
    "time": "2025-08-28"
  },
  {
    "open": 35.21,
    "close": 35.0,
    "high": 35.74,
    "low": 34.54,
    "volume": 46154,
    "time": "2025-08-29"
  },
  {
    "open": 35.5,
    "close": 35.74,
    "high": 35.88,
    "low": 34.8,
    "volume": 48961,
    "time": "2025-09-01"
  },
  {
    "open": 35.63,
    "close": 32.96,
    "high": 35.8,
    "low": 32.43,
    "volume": 112575,
    "time": "2025-09-02"
  },
  {
    "open": 32.96,
    "close": 32.28,
    "high": 33.48,
    "low": 32.27,
    "volume": 53673,
    "time": "2025-09-03"
  },
  {
    "open": 32.58,
    "close": 31.16,
    "high": 33.31,
    "low": 30.65,
    "volume": 52824,
    "time": "2025-09-04"
  },
  {
    "open": 31.16,
    "close": 32.62,
    "high": 32.65,
    "low": 31.16,
    "volume": 46676,
    "time": "2025-09-05"
  },
  {
    "open": 32.86,
    "close": 33.95,
    "high": 34.25,
    "low": 32.63,
    "volume": 50787,
    "time": "2025-09-08"
  },
  {
    "open": 33.66,
    "close": 33.38,
    "high": 33.96,
    "low": 32.89,
    "volume": 29803,
    "time": "2025-09-09"
  },
  {
    "open": 33.38,
    "close": 33.52,
    "high": 34.28,
    "low": 33.38,
    "volume": 24886,
    "time": "2025-09-10"
  },
  {
    "open": 33.24,
    "close": 34.11,
    "high": 34.25,
    "low": 33.05,
    "volume": 31303,
    "time": "2025-09-11"
  },
  {
    "open": 34.57,
    "close": 33.15,
    "high": 34.57,
    "low": 33.08,
    "volume": 35880,
    "time": "2025-09-12"
  },
  {
    "open": 33.24,
    "close": 33.09,
    "high": 33.38,
    "low": 32.23,
    "volume": 35750,
    "time": "2025-09-15"
  },
  {
    "open": 33.11,
    "close": 34.23,
    "high": 34.5,
    "low": 32.73,
    "volume": 40890,
    "time": "2025-09-16"
  },
  {
    "open": 33.94,
    "close": 34.92,
    "high": 35.34,
    "low": 33.94,
    "volume": 42623,
    "time": "2025-09-17"
  },
  {
    "open": 34.93,
    "close": 34.51,
    "high": 36.14,
    "low": 34.0,
    "volume": 57926,
    "time": "2025-09-18"
  },
  {
    "open": 34.51,
    "close": 33.82,
    "high": 35.12,
    "low": 33.23,
    "volume": 44161,
    "time": "2025-09-19"
  },
  {
    "open": 33.53,
    "close": 33.18,
    "high": 34.21,
    "low": 32.6,
    "volume": 91659,
    "time": "2025-09-22"
  },
  {
    "open": 33.3,
    "close": 32.8,
    "high": 33.5,
    "low": 31.88,
    "volume": 45631,
    "time": "2025-09-23"
  },
  {
    "open": 32.66,
    "close": 34.44,
    "high": 35.18,
    "low": 32.26,
    "volume": 86335,
    "time": "2025-09-24"
  },
  {
    "open": 34.72,
    "close": 36.0,
    "high": 36.47,
    "low": 34.23,
    "volume": 101409,
    "time": "2025-09-25"
  },
  {
    "open": 36.69,
    "close": 34.65,
    "high": 36.78,
    "low": 33.43,
    "volume": 118366,
    "time": "2025-09-26"
  },
  {
    "open": 34.87,
    "close": 33.42,
    "high": 34.89,
    "low": 33.4,
    "volume": 68157,
    "time": "2025-09-29"
  },
  {
    "open": 33.42,
    "close": 33.5,
    "high": 34.49,
    "low": 33.37,
    "volume": 37149,
    "time": "2025-09-30"
  },
  {
    "open": 34.0,
    "close": 34.33,
    "high": 35.67,
    "low": 33.62,
    "volume": 66355,
    "time": "2025-10-09"
  },
  {
    "open": 34.01,
    "close": 34.97,
    "high": 35.35,
    "low": 33.23,
    "volume": 69401,
    "time": "2025-10-10"
  },
  {
    "open": 33.5,
    "close": 34.68,
    "high": 34.78,
    "low": 32.64,
    "volume": 62476,
    "time": "2025-10-13"
  },
  {
    "open": 35.55,
    "close": 32.31,
    "high": 35.55,
    "low": 32.0,
    "volume": 72933,
    "time": "2025-10-14"
  },
  {
    "open": 32.49,
    "close": 33.08,
    "high": 33.15,
    "low": 32.31,
    "volume": 43090,
    "time": "2025-10-15"
  },
  {
    "open": 32.63,
    "close": 34.38,
    "high": 35.55,
    "low": 32.03,
    "volume": 86715,
    "time": "2025-10-16"
  },
  {
    "open": 34.39,
    "close": 33.71,
    "high": 34.74,
    "low": 33.55,
    "volume": 50542,
    "time": "2025-10-17"
  },
  {
    "open": 34.8,
    "close": 33.65,
    "high": 34.8,
    "low": 33.05,
    "volume": 36779,
    "time": "2025-10-20"
  },
  {
    "open": 33.42,
    "close": 34.79,
    "high": 35.5,
    "low": 33.42,
    "volume": 60232,
    "time": "2025-10-21"
  },
  {
    "open": 34.49,
    "close": 34.48,
    "high": 34.66,
    "low": 33.78,
    "volume": 39230,
    "time": "2025-10-22"
  },
  {
    "open": 34.4,
    "close": 33.51,
    "high": 34.4,
    "low": 33.18,
    "volume": 32323,
    "time": "2025-10-23"
  },
  {
    "open": 33.48,
    "close": 35.34,
    "high": 35.48,
    "low": 33.48,
    "volume": 75621,
    "time": "2025-10-24"
  },
  {
    "open": 35.88,
    "close": 34.96,
    "high": 35.91,
    "low": 34.61,
    "volume": 59599,
    "time": "2025-10-27"
  },
  {
    "open": 34.95,
    "close": 35.61,
    "high": 35.99,
    "low": 34.28,
    "volume": 74717,
    "time": "2025-10-28"
  },
  {
    "open": 35.5,
    "close": 35.14,
    "high": 35.6,
    "low": 34.66,
    "volume": 64964,
    "time": "2025-10-29"
  },
  {
    "open": 35.14,
    "close": 35.89,
    "high": 36.44,
    "low": 34.65,
    "volume": 77330,
    "time": "2025-10-30"
  },
  {
    "open": 35.74,
    "close": 37.27,
    "high": 37.9,
    "low": 35.45,
    "volume": 106911,
    "time": "2025-10-31"
  },
  {
    "open": 37.0,
    "close": 38.0,
    "high": 39.3,
    "low": 36.6,
    "volume": 99614,
    "time": "2025-11-03"
  },
  {
    "open": 37.76,
    "close": 37.26,
    "high": 38.15,
    "low": 37.03,
    "volume": 56771,
    "time": "2025-11-04"
  },
  {
    "open": 36.63,
    "close": 37.03,
    "high": 37.83,
    "low": 36.06,
    "volume": 54237,
    "time": "2025-11-05"
  },
  {
    "open": 37.5,
    "close": 37.0,
    "high": 37.78,
    "low": 35.92,
    "volume": 89899,
    "time": "2025-11-06"
  },
  {
    "open": 36.9,
    "close": 38.61,
    "high": 39.77,
    "low": 36.52,
    "volume": 101488,
    "time": "2025-11-07"
  },
  {
    "open": 38.81,
    "close": 41.69,
    "high": 42.0,
    "low": 38.44,
    "volume": 121108,
    "time": "2025-11-10"
  },
  {
    "open": 42.53,
    "close": 41.8,
    "high": 42.99,
    "low": 41.4,
    "volume": 100993,
    "time": "2025-11-11"
  },
  {
    "open": 42.33,
    "close": 41.76,
    "high": 42.69,
    "low": 41.35,
    "volume": 47037,
    "time": "2025-11-12"
  },
  {
    "open": 41.66,
    "close": 42.44,
    "high": 42.98,
    "low": 41.21,
    "volume": 58587,
    "time": "2025-11-13"
  },
  {
    "open": 42.44,
    "close": 41.59,
    "high": 43.26,
    "low": 41.38,
    "volume": 49133,
    "time": "2025-11-14"
  },
  {
    "open": 41.61,
    "close": 43.74,
    "high": 43.99,
    "low": 41.51,
    "volume": 69824,
    "time": "2025-11-17"
  },
  {
    "open": 44.01,
    "close": 41.92,
    "high": 45.68,
    "low": 41.7,
    "volume": 77415,
    "time": "2025-11-18"
  },
  {
    "open": 41.8,
    "close": 41.99,
    "high": 42.39,
    "low": 40.71,
    "volume": 85375,
    "time": "2025-11-19"
  },
  {
    "open": 42.21,
    "close": 41.84,
    "high": 42.64,
    "low": 41.53,
    "volume": 33495,
    "time": "2025-11-20"
  },
  {
    "open": 41.02,
    "close": 40.75,
    "high": 41.9,
    "low": 40.5,
    "volume": 43384,
    "time": "2025-11-21"
  },
  {
    "open": 40.8,
    "close": 41.9,
    "high": 42.5,
    "low": 40.4,
    "volume": 37785,
    "time": "2025-11-24"
  },
  {
    "open": 42.3,
    "close": 41.99,
    "high": 42.76,
    "low": 41.79,
    "volume": 31733,
    "time": "2025-11-25"
  },
  {
    "open": 41.9,
    "close": 42.28,
    "high": 42.93,
    "low": 41.42,
    "volume": 32880,
    "time": "2025-11-26"
  },
  {
    "open": 42.47,
    "close": 43.5,
    "high": 43.89,
    "low": 42.28,
    "volume": 40533,
    "time": "2025-11-27"
  },
  {
    "open": 43.43,
    "close": 43.97,
    "high": 43.99,
    "low": 42.66,
    "volume": 30645,
    "time": "2025-11-28"
  },
  {
    "open": 43.6,
    "close": 45.35,
    "high": 45.88,
    "low": 43.6,
    "volume": 54194,
    "time": "2025-12-01"
  },
  {
    "open": 45.35,
    "close": 45.0,
    "high": 45.69,
    "low": 44.7,
    "volume": 26248,
    "time": "2025-12-02"
  },
  {
    "open": 45.11,
    "close": 44.39,
    "high": 45.27,
    "low": 43.9,
    "volume": 29800,
    "time": "2025-12-03"
  },
  {
    "open": 44.23,
    "close": 44.19,
    "high": 44.8,
    "low": 43.81,
    "volume": 25514,
    "time": "2025-12-04"
  },
  {
    "open": 44.42,
    "close": 45.36,
    "high": 45.4,
    "low": 43.5,
    "volume": 28658,
    "time": "2025-12-05"
  },
  {
    "open": 45.44,
    "close": 46.7,
    "high": 47.06,
    "low": 45.44,
    "volume": 34702,
    "time": "2025-12-08"
  },
  {
    "open": 46.4,
    "close": 44.5,
    "high": 46.99,
    "low": 43.6,
    "volume": 70388,
    "time": "2025-12-09"
  },
  {
    "open": 44.8,
    "close": 44.3,
    "high": 45.89,
    "low": 43.88,
    "volume": 46101,
    "time": "2025-12-10"
  },
  {
    "open": 44.57,
    "close": 43.15,
    "high": 44.7,
    "low": 43.01,
    "volume": 36945,
    "time": "2025-12-11"
  },
  {
    "open": 43.16,
    "close": 42.6,
    "high": 43.38,
    "low": 42.21,
    "volume": 28487,
    "time": "2025-12-12"
  },
  {
    "open": 42.6,
    "close": 41.88,
    "high": 42.81,
    "low": 41.61,
    "volume": 32490,
    "time": "2025-12-15"
  },
  {
    "open": 42.0,
    "close": 42.78,
    "high": 42.98,
    "low": 40.3,
    "volume": 40874,
    "time": "2025-12-16"
  },
  {
    "open": 42.89,
    "close": 42.26,
    "high": 43.77,
    "low": 41.7,
    "volume": 36776,
    "time": "2025-12-17"
  },
  {
    "open": 42.0,
    "close": 42.33,
    "high": 42.83,
    "low": 41.6,
    "volume": 16286,
    "time": "2025-12-18"
  },
  {
    "open": 42.34,
    "close": 42.94,
    "high": 43.66,
    "low": 42.34,
    "volume": 18832,
    "time": "2025-12-19"
  },
  {
    "open": 42.9,
    "close": 44.36,
    "high": 44.65,
    "low": 42.51,
    "volume": 24022,
    "time": "2025-12-22"
  },
  {
    "open": 44.01,
    "close": 44.26,
    "high": 44.84,
    "low": 43.85,
    "volume": 19451,
    "time": "2025-12-23"
  },
  {
    "open": 44.52,
    "close": 45.82,
    "high": 46.48,
    "low": 44.01,
    "volume": 35873,
    "time": "2025-12-24"
  },
  {
    "open": 45.93,
    "close": 47.32,
    "high": 48.1,
    "low": 45.66,
    "volume": 38537,
    "time": "2025-12-25"
  },
  {
    "open": 47.26,
    "close": 47.18,
    "high": 48.75,
    "low": 46.8,
    "volume": 34587,
    "time": "2025-12-26"
  },
  {
    "open": 47.42,
    "close": 47.3,
    "high": 48.88,
    "low": 46.27,
    "volume": 49692,
    "time": "2025-12-29"
  },
  {
    "open": 47.34,
    "close": 49.08,
    "high": 49.36,
    "low": 46.17,
    "volume": 51551,
    "time": "2025-12-30"
  },
  {
    "open": 48.66,
    "close": 48.1,
    "high": 49.25,
    "low": 47.9,
    "volume": 30606,
    "time": "2025-12-31"
  },
  {
    "open": 48.32,
    "close": 48.2,
    "high": 48.75,
    "low": 47.0,
    "volume": 54406,
    "time": "2026-01-05"
  },
  {
    "open": 48.44,
    "close": 47.06,
    "high": 48.88,
    "low": 46.74,
    "volume": 62386,
    "time": "2026-01-06"
  },
  {
    "open": 47.07,
    "close": 46.49,
    "high": 47.99,
    "low": 45.98,
    "volume": 62866,
    "time": "2026-01-07"
  },
  {
    "open": 46.8,
    "close": 47.26,
    "high": 47.76,
    "low": 46.12,
    "volume": 47732,
    "time": "2026-01-08"
  },
  {
    "open": 47.3,
    "close": 51.13,
    "high": 51.2,
    "low": 47.0,
    "volume": 84986,
    "time": "2026-01-09"
  },
  {
    "open": 51.13,
    "close": 53.01,
    "high": 53.68,
    "low": 49.24,
    "volume": 94860,
    "time": "2026-01-12"
  },
  {
    "open": 54.07,
    "close": 52.05,
    "high": 56.99,
    "low": 51.8,
    "volume": 110903,
    "time": "2026-01-13"
  },
  {
    "open": 53.44,
    "close": 49.23,
    "high": 53.9,
    "low": 47.5,
    "volume": 117289,
    "time": "2026-01-14"
  },
  {
    "open": 48.75,
    "close": 49.03,
    "high": 49.5,
    "low": 48.0,
    "volume": 36713,
    "time": "2026-01-15"
  },
  {
    "open": 49.0,
    "close": 48.72,
    "high": 49.25,
    "low": 48.0,
    "volume": 29829,
    "time": "2026-01-16"
  },
  {
    "open": 48.69,
    "close": 48.35,
    "high": 48.74,
    "low": 47.74,
    "volume": 40992,
    "time": "2026-01-19"
  },
  {
    "open": 48.26,
    "close": 47.59,
    "high": 48.32,
    "low": 46.3,
    "volume": 38282,
    "time": "2026-01-20"
  },
  {
    "open": 47.5,
    "close": 48.2,
    "high": 48.5,
    "low": 46.55,
    "volume": 32873,
    "time": "2026-01-21"
  },
  {
    "open": 48.5,
    "close": 47.93,
    "high": 48.5,
    "low": 46.97,
    "volume": 26073,
    "time": "2026-01-22"
  },
  {
    "open": 48.1,
    "close": 50.84,
    "high": 51.5,
    "low": 47.3,
    "volume": 52341,
    "time": "2026-01-23"
  },
  {
    "open": 50.6,
    "close": 50.72,
    "high": 51.46,
    "low": 49.8,
    "volume": 44889,
    "time": "2026-01-26"
  },
  {
    "open": 50.59,
    "close": 49.39,
    "high": 50.97,
    "low": 47.39,
    "volume": 41399,
    "time": "2026-01-27"
  },
  {
    "open": 49.67,
    "close": 48.18,
    "high": 49.68,
    "low": 47.78,
    "volume": 30689,
    "time": "2026-01-28"
  },
  {
    "open": 47.99,
    "close": 47.9,
    "high": 49.61,
    "low": 47.0,
    "volume": 43116,
    "time": "2026-01-29"
  },
  {
    "open": 47.8,
    "close": 47.48,
    "high": 48.32,
    "low": 45.5,
    "volume": 48225,
    "time": "2026-01-30"
  },
  {
    "open": 46.58,
    "close": 46.49,
    "high": 47.6,
    "low": 45.41,
    "volume": 42528,
    "time": "2026-02-02"
  },
  {
    "open": 46.64,
    "close": 46.76,
    "high": 47.25,
    "low": 46.31,
    "volume": 23670,
    "time": "2026-02-03"
  },
  {
    "open": 46.86,
    "close": 45.49,
    "high": 46.86,
    "low": 45.23,
    "volume": 26548,
    "time": "2026-02-04"
  },
  {
    "open": 45.3,
    "close": 45.53,
    "high": 46.01,
    "low": 44.8,
    "volume": 16825,
    "time": "2026-02-05"
  },
  {
    "open": 45.47,
    "close": 45.6,
    "high": 46.36,
    "low": 44.94,
    "volume": 21446,
    "time": "2026-02-06"
  },
  {
    "open": 46.21,
    "close": 45.42,
    "high": 46.3,
    "low": 45.01,
    "volume": 25562,
    "time": "2026-02-09"
  },
  {
    "open": 45.33,
    "close": 44.99,
    "high": 45.64,
    "low": 44.66,
    "volume": 18954,
    "time": "2026-02-10"
  },
  {
    "open": 45.0,
    "close": 45.78,
    "high": 46.38,
    "low": 44.54,
    "volume": 28882,
    "time": "2026-02-11"
  },
  {
    "open": 45.88,
    "close": 45.05,
    "high": 45.88,
    "low": 44.6,
    "volume": 21267,
    "time": "2026-02-12"
  },
  {
    "open": 45.03,
    "close": 45.14,
    "high": 45.61,
    "low": 44.62,
    "volume": 23498,
    "time": "2026-02-13"
  },
  {
    "open": 45.5,
    "close": 45.8,
    "high": 46.15,
    "low": 44.89,
    "volume": 21953,
    "time": "2026-02-24"
  },
  {
    "open": 45.53,
    "close": 46.23,
    "high": 46.63,
    "low": 45.3,
    "volume": 24271,
    "time": "2026-02-25"
  },
  {
    "open": 46.23,
    "close": 50.2,
    "high": 50.88,
    "low": 45.28,
    "volume": 113220,
    "time": "2026-02-26"
  }
]